cliai/.DS_Store
cliai/__init__.py
cliai/cli.py
cliai/config.py
cliai/convo.py
cliai/core.py
cliai/embedding.py
cliai/stream.py
cliai/text.txt
cliai/util.py
cliai-0.2.9.dist-info/LICENSE
cliai-0.2.9.dist-info/METADATA
cliai-0.2.9.dist-info/WHEEL
cliai-0.2.9.dist-info/entry_points.txt
cliai-0.2.9.dist-info/RECORD
