Metadata-Version: 2.1
Name: cliai
Version: 0.2.9
Summary: Command-line interface for OpenAI ChatGPT
License: GPL-3.0-or-later
Author: Baksi Li
Author-email: myself@baksili.codes
Requires-Python: >=3.8,<4.0
Classifier: License :: OSI Approved :: GNU General Public License v3 or later (GPLv3+)
Classifier: Programming Language :: Python :: 3
Classifier: Programming Language :: Python :: 3.8
Classifier: Programming Language :: Python :: 3.9
Classifier: Programming Language :: Python :: 3.10
Classifier: Programming Language :: Python :: 3.11
Requires-Dist: click (>=8.1.3,<9.0.0)
Requires-Dist: click-aliases (>=1.0.1,<2.0.0)
Requires-Dist: openai (>=0.27.1,<0.28.0)
Requires-Dist: pygments (>=2.14.0,<3.0.0)
Requires-Dist: questionary (>=1.10.0,<2.0.0)
